IQCommon/__init__.py
IQCommon/arg_checker.py
IQCommon/const.py
IQCommon/datetime_func.py
IQCommon/encrypt.py
IQCommon/exception.py
IQCommon/i18n.py
IQCommon/pycompatibility.py
IQCommon/trade_schedule.py
IQCommon/utils.py
IQCommon/version.py
IQCommon/api/__init__.py
IQCommon/api/wrapper.py
IQCommon/data/__init__.py
IQCommon/data/pandas.py
IQCommon/logger/__init__.py
IQCommon/logger/handlers.py
IQData/__init__.py
IQData/interface.py
IQData/version.py
IQData/apis/__init__.py
IQData/apis/authentication.py
IQData/services/__init__.py
IQData/services/factor_gtn/__init__.py
IQData/services/factor_gtn/api.py
IQData/services/factor_gtn/const.py
IQData/services/factor_gtn/factor_gtn.py
IQData/services/gtn_client/__init__.py
IQData/services/gtn_client/api.py
IQData/services/gtn_client/base_http_client.py
IQData/services/gtn_client/gtn_client.py
IQData/services/gtn_client/ibrain_client.py
IQData/services/gtn_client/web_socket_client.py
IQData/utils/__init__.py
IQData/utils/cache_storage.py
IQData/utils/config.py
IQData/utils/default_config.yml
IQData/utils/encrypt.py
IQData/utils/module_object.py
IQData-1.1.3.dist-info/DESCRIPTION.rst
IQData-1.1.3.dist-info/METADATA
IQData-1.1.3.dist-info/RECORD
IQData-1.1.3.dist-info/WHEEL
IQData-1.1.3.dist-info/entry_points.txt
IQData-1.1.3.dist-info/metadata.json
IQData-1.1.3.dist-info/top_level.txt
