Metadata-Version: 2.0
Name: IQData
Version: 1.1.3
Summary: UNKNOWN
Home-page: UNKNOWN
Author: hundsun
Author-email: service.hsri@hundsun.com
License: UNKNOWN
Keywords: Quant Data Interface
Platform: UNKNOWN
Classifier: Intended Audience :: Developers
Classifier: License :: OSI Approved :: GNU General Public License (GPL)
Classifier: Programming Language :: Python
Classifier: Operating System :: Microsoft :: Windows
Classifier: Programming Language :: Python :: 3.5
Classifier: Programming Language :: Python :: 3.6
Classifier: Programming Language :: Python :: 3.7
Requires-Dist: Logbook (>=1.4.1)
Requires-Dist: PyYAML (>=3.13)
Requires-Dist: cryptography (>=1.5)
Requires-Dist: numpy (>=1.15.4)
Requires-Dist: pandas (>=0.23.4)
Requires-Dist: pycryptodome (>=3.5.0)
Requires-Dist: python-dateutil (>=2.7.5)
Requires-Dist: requests (>=2.21.0)
Requires-Dist: ruamel.yaml (>=0.15.90)
Requires-Dist: six (>=1.12.0)
Requires-Dist: websocket-client (>=0.40.0)
